setup.py
webullsdk/__init__.py
webullsdk/calendar.py
webullsdk/capitalflow.py
webullsdk/etf_finder.py
webullsdk/financial_statement.py
webullsdk/institutional_holdings.py
webullsdk/manage.py
webullsdk/news.py
webullsdk/shortinterest.py
webullsdk/top_options.py
webullsdk/webull_data.py
webullsdk/webullsdk.py
webullsdk.egg-info/PKG-INFO
webullsdk.egg-info/SOURCES.txt
webullsdk.egg-info/dependency_links.txt
webullsdk.egg-info/requires.txt
webullsdk.egg-info/top_level.txt